whoopi/__init__.py
whoopi/constants.py
whoopi/version.py
whoopi/whoopi.py
whoopi-1.0.0.dist-info/LICENSE
whoopi-1.0.0.dist-info/METADATA
whoopi-1.0.0.dist-info/WHEEL
whoopi-1.0.0.dist-info/top_level.txt
whoopi-1.0.0.dist-info/RECORD
