Metadata-Version: 2.1
Name: whoopi
Version: 1.0.0
Summary: Whoopi python SDK
Home-page: https://github.com/0verread/whoopi-py
Author: Subhajit Das
Author-email: iamsubhajit.d@gmail.com
License: MIT
Requires-Python: >=3.6
License-File: LICENSE
Requires-Dist: requests
